length_tokenizer_rs-0.1.10.dist-info/METADATA
length_tokenizer_rs-0.1.10.dist-info/WHEEL
length_tokenizer_rs-0.1.10.dist-info/licenses/LICENSE
length_tokenizer_rs/__init__.py
length_tokenizer_rs/length_tokenizer_rs.cpython-310-darwin.so
length_tokenizer_rs-0.1.10.dist-info/RECORD
