Metadata-Version: 2.4
Name: length-tokenizer-rs
Version: 0.1.10
Classifier: Programming Language :: Python :: 3
Classifier: Programming Language :: Rust
Classifier: License :: OSI Approved :: MIT License
Classifier: Operating System :: OS Independent
License-File: LICENSE
Summary: LengthTokenizer Rust (DP 最少 token / 最低 TPC) Python extension
Requires-Python: >=3.8
